testpypippietruszka/__init__.py
testpypippietruszka/m_mod_pp.py
testpypippietruszka-0.0.1.dist-info/LICENSE.txt
testpypippietruszka-0.0.1.dist-info/METADATA
testpypippietruszka-0.0.1.dist-info/WHEEL
testpypippietruszka-0.0.1.dist-info/top_level.txt
testpypippietruszka-0.0.1.dist-info/RECORD
