Metadata-Version: 2.1
Name: testpypippietruszka
Version: 0.0.1
Summary: My test package
Author-email: PiotrPP <piotrpietruszka@protonmail.com>
License: MIT License
Keywords: testpypippietruszka,name,surename,fun function
Classifier: Operating System :: POSIX :: Other
Classifier: Programming Language :: Python
Requires-Python: >=3.0
License-File: LICENSE.txt
Requires-Dist: numpy
